CrawlFlow/handler.py
CrawlFlow/types.py
CrawlFlow-0.2.2.dist-info/LICENSE
CrawlFlow-0.2.2.dist-info/METADATA
CrawlFlow-0.2.2.dist-info/WHEEL
CrawlFlow-0.2.2.dist-info/top_level.txt
CrawlFlow-0.2.2.dist-info/RECORD
